posthaste/__init__.py
posthaste/__main__.py
posthaste_cli-0.1.0.dist-info/licenses/LICENSE
posthaste_cli-0.1.0.dist-info/METADATA
posthaste_cli-0.1.0.dist-info/WHEEL
posthaste_cli-0.1.0.dist-info/entry_points.txt
posthaste_cli-0.1.0.dist-info/top_level.txt
posthaste_cli-0.1.0.dist-info/RECORD
