Metadata-Version: 2.4
Name: posthaste-cli
Version: 0.1.0
Summary: A CLI tool to upload text to a hastebin server quickly and cleanly.
Home-page: https://github.com/ArchooD2/posthaste
Author: PJ Hayes
Author-email: archood2next@gmail.com
Classifier: Programming Language :: Python :: 3
Classifier: License :: OSI Approved :: MIT License
Classifier: Operating System :: OS Independent
Requires-Python: >=3.7
License-File: LICENSE
Requires-Dist: requests
Requires-Dist: snaparg
Dynamic: author
Dynamic: author-email
Dynamic: classifier
Dynamic: description
Dynamic: description-content-type
Dynamic: home-page
Dynamic: license-file
Dynamic: requires-dist
Dynamic: requires-python
Dynamic: summary
